[
    {
        "inputs": [
            {
                "internalType": "address",
                "name": "_currency",
                "type": "address"
            }
        ],
        "stateMutability": "nonpayable",
        "type": "constructor"
    },
    {
        "anonymous": false,
        "inputs": [
            {
                "indexed": false,
                "internalType": "uint256",
                "name": "jobId",
                "type": "uint256"
            },
            {
                "indexed": true,
                "internalType": "address",
                "name": "freelancer",
                "type": "address"
            }
        ],
        "name": "ContractAccepted",
        "type": "event"
    },
    {
        "anonymous": false,
        "inputs": [
            {
                "indexed": false,
                "internalType": "uint256",
                "name": "jobId",
                "type": "uint256"
            },
            {
                "indexed": true,
                "internalType": "address",
                "name": "freelancer",
                "type": "address"
            }
        ],
        "name": "ContractSent",
        "type": "event"
    },
    {
        "anonymous": false,
        "inputs": [
            {
                "indexed": false,
                "internalType": "uint256",
                "name": "jobId",
                "type": "uint256"
            },
            {
                "indexed": false,
                "internalType": "uint256",
                "name": "amount",
                "type": "uint256"
            },
            {
                "indexed": false,
                "internalType": "string",
                "name": "title",
                "type": "string"
            }
        ],
        "name": "DisputeOpened",
        "type": "event"
    },
    {
        "anonymous": false,
        "inputs": [
            {
                "indexed": false,
                "internalType": "uint256",
                "name": "jobId",
                "type": "uint256"
            },
            {
                "indexed": false,
                "internalType": "uint256",
                "name": "amount",
                "type": "uint256"
            },
            {
                "indexed": false,
                "internalType": "string",
                "name": "title",
                "type": "string"
            }
        ],
        "name": "JobCancelled",
        "type": "event"
    },
    {
        "anonymous": false,
        "inputs": [
            {
                "indexed": false,
                "internalType": "uint256",
                "name": "jobId",
                "type": "uint256"
            },
            {
                "indexed": false,
                "internalType": "string",
                "name": "message",
                "type": "string"
            },
            {
                "indexed": true,
                "internalType": "address",
                "name": "freelancer",
                "type": "address"
            }
        ],
        "name": "JobCompleted",
        "type": "event"
    },
    {
        "anonymous": false,
        "inputs": [
            {
                "indexed": false,
                "internalType": "uint256",
                "name": "jobId",
                "type": "uint256"
            },
            {
                "indexed": false,
                "internalType": "string",
                "name": "title",
                "type": "string"
            },
            {
                "indexed": false,
                "internalType": "uint256",
                "name": "amount",
                "type": "uint256"
            },
            {
                "indexed": false,
                "internalType": "string",
                "name": "description",
                "type": "string"
            },
            {
                "indexed": false,
                "internalType": "uint256",
                "name": "timeline",
                "type": "uint256"
            },
            {
                "indexed": true,
                "internalType": "address",
                "name": "client",
                "type": "address"
            }
        ],
        "name": "JobPosted",
        "type": "event"
    },
    {
        "anonymous": false,
        "inputs": [
            {
                "indexed": false,
                "internalType": "uint256",
                "name": "jobId",
                "type": "uint256"
            },
            {
                "indexed": false,
                "internalType": "uint256",
                "name": "amount",
                "type": "uint256"
            },
            {
                "indexed": false,
                "internalType": "string",
                "name": "title",
                "type": "string"
            }
        ],
        "name": "OfferDeclined",
        "type": "event"
    },
    {
        "anonymous": false,
        "inputs": [
            {
                "indexed": false,
                "internalType": "uint256",
                "name": "jobId",
                "type": "uint256"
            },
            {
                "indexed": false,
                "internalType": "uint256",
                "name": "amount",
                "type": "uint256"
            }
        ],
        "name": "OfferWithDrawn",
        "type": "event"
    },
    {
        "anonymous": false,
        "inputs": [
            {
                "indexed": true,
                "internalType": "address",
                "name": "previousOwner",
                "type": "address"
            },
            {
                "indexed": true,
                "internalType": "address",
                "name": "newOwner",
                "type": "address"
            }
        ],
        "name": "OwnershipTransferred",
        "type": "event"
    },
    {
        "anonymous": false,
        "inputs": [
            {
                "indexed": false,
                "internalType": "uint256",
                "name": "jobId",
                "type": "uint256"
            },
            {
                "indexed": false,
                "internalType": "uint256",
                "name": "amount",
                "type": "uint256"
            },
            {
                "indexed": true,
                "internalType": "address",
                "name": "freelancer",
                "type": "address"
            }
        ],
        "name": "PayementReleased",
        "type": "event"
    },
    {
        "anonymous": false,
        "inputs": [
            {
                "indexed": true,
                "internalType": "address",
                "name": "user",
                "type": "address"
            },
            {
                "indexed": false,
                "internalType": "string",
                "name": "name",
                "type": "string"
            },
            {
                "indexed": false,
                "internalType": "string",
                "name": "skill",
                "type": "string"
            }
        ],
        "name": "ProfileCreated",
        "type": "event"
    },
    {
        "anonymous": false,
        "inputs": [
            {
                "indexed": false,
                "internalType": "uint256",
                "name": "jobId",
                "type": "uint256"
            },
            {
                "indexed": false,
                "internalType": "string",
                "name": "description",
                "type": "string"
            },
            {
                "indexed": true,
                "internalType": "address",
                "name": "client",
                "type": "address"
            }
        ],
        "name": "ProposalSubmitted",
        "type": "event"
    },
    {
        "anonymous": false,
        "inputs": [
            {
                "indexed": true,
                "internalType": "address",
                "name": "client",
                "type": "address"
            },
            {
                "indexed": false,
                "internalType": "string",
                "name": "meassge",
                "type": "string"
            },
            {
                "indexed": false,
                "internalType": "uint256",
                "name": "rating",
                "type": "uint256"
            }
        ],
        "name": "ReviewCreated",
        "type": "event"
    },
    {
        "inputs": [],
        "name": "USDC",
        "outputs": [
            {
                "internalType": "contract IERC20",
                "name": "",
                "type": "address"
            }
        ],
        "stateMutability": "view",
        "type": "function"
    },
    {
        "inputs": [
            {
                "internalType": "uint256",
                "name": "jobId",
                "type": "uint256"
            }
        ],
        "name": "acceptContract",
        "outputs": [
            {
                "components": [
                    {
                        "internalType": "uint256",
                        "name": "jobId",
                        "type": "uint256"
                    },
                    {
                        "internalType": "string",
                        "name": "description",
                        "type": "string"
                    },
                    {
                        "internalType": "uint256",
                        "name": "timeline",
                        "type": "uint256"
                    },
                    {
                        "internalType": "address",
                        "name": "freelancer",
                        "type": "address"
                    },
                    {
                        "internalType": "enum BidState",
                        "name": "bidState",
                        "type": "uint8"
                    }
                ],
                "internalType": "struct Bid",
                "name": "",
                "type": "tuple"
            }
        ],
        "stateMutability": "nonpayable",
        "type": "function"
    },
    {
        "inputs": [],
        "name": "balance",
        "outputs": [
            {
                "internalType": "uint256",
                "name": "",
                "type": "uint256"
            }
        ],
        "stateMutability": "view",
        "type": "function"
    },
    {
        "inputs": [
            {
                "internalType": "uint256",
                "name": "jobId",
                "type": "uint256"
            }
        ],
        "name": "cancelJob",
        "outputs": [
            {
                "components": [
                    {
                        "internalType": "uint256",
                        "name": "jobId",
                        "type": "uint256"
                    },
                    {
                        "internalType": "string",
                        "name": "title",
                        "type": "string"
                    },
                    {
                        "internalType": "string",
                        "name": "description",
                        "type": "string"
                    },
                    {
                        "internalType": "uint256",
                        "name": "amount",
                        "type": "uint256"
                    },
                    {
                        "internalType": "address",
                        "name": "client",
                        "type": "address"
                    },
                    {
                        "internalType": "string[]",
                        "name": "skills",
                        "type": "string[]"
                    },
                    {
                        "internalType": "uint256",
                        "name": "timeline",
                        "type": "uint256"
                    },
                    {
                        "internalType": "address",
                        "name": "freelancer",
                        "type": "address"
                    },
                    {
                        "components": [
                            {
                                "internalType": "uint256",
                                "name": "jobId",
                                "type": "uint256"
                            },
                            {
                                "internalType": "string",
                                "name": "description",
                                "type": "string"
                            },
                            {
                                "internalType": "uint256",
                                "name": "timeline",
                                "type": "uint256"
                            },
                            {
                                "internalType": "address",
                                "name": "freelancer",
                                "type": "address"
                            },
                            {
                                "internalType": "enum BidState",
                                "name": "bidState",
                                "type": "uint8"
                            }
                        ],
                        "internalType": "struct Bid[]",
                        "name": "userBids",
                        "type": "tuple[]"
                    },
                    {
                        "internalType": "uint256",
                        "name": "timestamp",
                        "type": "uint256"
                    },
                    {
                        "internalType": "enum JobState",
                        "name": "state",
                        "type": "uint8"
                    },
                    {
                        "internalType": "string",
                        "name": "message",
                        "type": "string"
                    },
                    {
                        "internalType": "string",
                        "name": "url",
                        "type": "string"
                    }
                ],
                "internalType": "struct Job[]",
                "name": "",
                "type": "tuple[]"
            }
        ],
        "stateMutability": "nonpayable",
        "type": "function"
    },
    {
        "inputs": [],
        "name": "commission",
        "outputs": [
            {
                "internalType": "uint256",
                "name": "",
                "type": "uint256"
            }
        ],
        "stateMutability": "view",
        "type": "function"
    },
    {
        "inputs": [
            {
                "internalType": "string",
                "name": "title",
                "type": "string"
            },
            {
                "internalType": "string",
                "name": "description",
                "type": "string"
            },
            {
                "internalType": "string[]",
                "name": "skills",
                "type": "string[]"
            },
            {
                "internalType": "uint256",
                "name": "timeline",
                "type": "uint256"
            },
            {
                "internalType": "uint256",
                "name": "amount",
                "type": "uint256"
            }
        ],
        "name": "createJobPost",
        "outputs": [
            {
                "internalType": "uint256",
                "name": "",
                "type": "uint256"
            }
        ],
        "stateMutability": "payable",
        "type": "function"
    },
    {
        "inputs": [
            {
                "internalType": "string",
                "name": "name",
                "type": "string"
            },
            {
                "internalType": "string",
                "name": "bio",
                "type": "string"
            },
            {
                "internalType": "string",
                "name": "mainSkill",
                "type": "string"
            },
            {
                "internalType": "string[]",
                "name": "skills",
                "type": "string[]"
            },
            {
                "internalType": "string",
                "name": "profileUrl",
                "type": "string"
            }
        ],
        "name": "createProfile",
        "outputs": [],
        "stateMutability": "nonpayable",
        "type": "function"
    },
    {
        "inputs": [
            {
                "internalType": "uint256",
                "name": "jobId",
                "type": "uint256"
            },
            {
                "internalType": "string",
                "name": "review",
                "type": "string"
            },
            {
                "internalType": "uint256",
                "name": "rating",
                "type": "uint256"
            }
        ],
        "name": "createReview",
        "outputs": [],
        "stateMutability": "nonpayable",
        "type": "function"
    },
    {
        "inputs": [
            {
                "internalType": "uint256",
                "name": "jobId",
                "type": "uint256"
            },
            {
                "internalType": "address",
                "name": "user",
                "type": "address"
            }
        ],
        "name": "creditUser",
        "outputs": [
            {
                "components": [
                    {
                        "internalType": "uint256",
                        "name": "jobId",
                        "type": "uint256"
                    },
                    {
                        "internalType": "string",
                        "name": "title",
                        "type": "string"
                    },
                    {
                        "internalType": "string",
                        "name": "description",
                        "type": "string"
                    },
                    {
                        "internalType": "uint256",
                        "name": "amount",
                        "type": "uint256"
                    },
                    {
                        "internalType": "address",
                        "name": "client",
                        "type": "address"
                    },
                    {
                        "internalType": "string[]",
                        "name": "skills",
                        "type": "string[]"
                    },
                    {
                        "internalType": "uint256",
                        "name": "timeline",
                        "type": "uint256"
                    },
                    {
                        "internalType": "address",
                        "name": "freelancer",
                        "type": "address"
                    },
                    {
                        "components": [
                            {
                                "internalType": "uint256",
                                "name": "jobId",
                                "type": "uint256"
                            },
                            {
                                "internalType": "string",
                                "name": "description",
                                "type": "string"
                            },
                            {
                                "internalType": "uint256",
                                "name": "timeline",
                                "type": "uint256"
                            },
                            {
                                "internalType": "address",
                                "name": "freelancer",
                                "type": "address"
                            },
                            {
                                "internalType": "enum BidState",
                                "name": "bidState",
                                "type": "uint8"
                            }
                        ],
                        "internalType": "struct Bid[]",
                        "name": "userBids",
                        "type": "tuple[]"
                    },
                    {
                        "internalType": "uint256",
                        "name": "timestamp",
                        "type": "uint256"
                    },
                    {
                        "internalType": "enum JobState",
                        "name": "state",
                        "type": "uint8"
                    },
                    {
                        "internalType": "string",
                        "name": "message",
                        "type": "string"
                    },
                    {
                        "internalType": "string",
                        "name": "url",
                        "type": "string"
                    }
                ],
                "internalType": "struct Job",
                "name": "",
                "type": "tuple"
            }
        ],
        "stateMutability": "nonpayable",
        "type": "function"
    },
    {
        "inputs": [
            {
                "internalType": "uint256",
                "name": "jobId",
                "type": "uint256"
            }
        ],
        "name": "declineOffer",
        "outputs": [
            {
                "components": [
                    {
                        "internalType": "uint256",
                        "name": "jobId",
                        "type": "uint256"
                    },
                    {
                        "internalType": "string",
                        "name": "title",
                        "type": "string"
                    },
                    {
                        "internalType": "string",
                        "name": "description",
                        "type": "string"
                    },
                    {
                        "internalType": "uint256",
                        "name": "amount",
                        "type": "uint256"
                    },
                    {
                        "internalType": "address",
                        "name": "client",
                        "type": "address"
                    },
                    {
                        "internalType": "string[]",
                        "name": "skills",
                        "type": "string[]"
                    },
                    {
                        "internalType": "uint256",
                        "name": "timeline",
                        "type": "uint256"
                    },
                    {
                        "internalType": "address",
                        "name": "freelancer",
                        "type": "address"
                    },
                    {
                        "components": [
                            {
                                "internalType": "uint256",
                                "name": "jobId",
                                "type": "uint256"
                            },
                            {
                                "internalType": "string",
                                "name": "description",
                                "type": "string"
                            },
                            {
                                "internalType": "uint256",
                                "name": "timeline",
                                "type": "uint256"
                            },
                            {
                                "internalType": "address",
                                "name": "freelancer",
                                "type": "address"
                            },
                            {
                                "internalType": "enum BidState",
                                "name": "bidState",
                                "type": "uint8"
                            }
                        ],
                        "internalType": "struct Bid[]",
                        "name": "userBids",
                        "type": "tuple[]"
                    },
                    {
                        "internalType": "uint256",
                        "name": "timestamp",
                        "type": "uint256"
                    },
                    {
                        "internalType": "enum JobState",
                        "name": "state",
                        "type": "uint8"
                    },
                    {
                        "internalType": "string",
                        "name": "message",
                        "type": "string"
                    },
                    {
                        "internalType": "string",
                        "name": "url",
                        "type": "string"
                    }
                ],
                "internalType": "struct Job",
                "name": "",
                "type": "tuple"
            }
        ],
        "stateMutability": "nonpayable",
        "type": "function"
    },
    {
        "inputs": [
            {
                "internalType": "uint256",
                "name": "jobId",
                "type": "uint256"
            }
        ],
        "name": "getJobBids",
        "outputs": [
            {
                "components": [
                    {
                        "internalType": "uint256",
                        "name": "jobId",
                        "type": "uint256"
                    },
                    {
                        "internalType": "string",
                        "name": "description",
                        "type": "string"
                    },
                    {
                        "internalType": "uint256",
                        "name": "timeline",
                        "type": "uint256"
                    },
                    {
                        "internalType": "address",
                        "name": "freelancer",
                        "type": "address"
                    },
                    {
                        "internalType": "enum BidState",
                        "name": "bidState",
                        "type": "uint8"
                    }
                ],
                "internalType": "struct Bid[]",
                "name": "",
                "type": "tuple[]"
            }
        ],
        "stateMutability": "view",
        "type": "function"
    },
    {
        "inputs": [],
        "name": "getListPrice",
        "outputs": [
            {
                "internalType": "uint256",
                "name": "",
                "type": "uint256"
            }
        ],
        "stateMutability": "view",
        "type": "function"
    },
    {
        "inputs": [
            {
                "internalType": "address",
                "name": "user",
                "type": "address"
            }
        ],
        "name": "getReviews",
        "outputs": [
            {
                "components": [
                    {
                        "internalType": "uint256",
                        "name": "jobId",
                        "type": "uint256"
                    },
                    {
                        "internalType": "address",
                        "name": "freelancer",
                        "type": "address"
                    },
                    {
                        "internalType": "string",
                        "name": "review",
                        "type": "string"
                    },
                    {
                        "internalType": "uint256",
                        "name": "rating",
                        "type": "uint256"
                    },
                    {
                        "internalType": "address",
                        "name": "client",
                        "type": "address"
                    }
                ],
                "internalType": "struct Review[]",
                "name": "",
                "type": "tuple[]"
            }
        ],
        "stateMutability": "view",
        "type": "function"
    },
    {
        "inputs": [],
        "name": "getTotalJobs",
        "outputs": [
            {
                "components": [
                    {
                        "internalType": "uint256",
                        "name": "jobId",
                        "type": "uint256"
                    },
                    {
                        "internalType": "string",
                        "name": "title",
                        "type": "string"
                    },
                    {
                        "internalType": "string",
                        "name": "description",
                        "type": "string"
                    },
                    {
                        "internalType": "uint256",
                        "name": "amount",
                        "type": "uint256"
                    },
                    {
                        "internalType": "address",
                        "name": "client",
                        "type": "address"
                    },
                    {
                        "internalType": "string[]",
                        "name": "skills",
                        "type": "string[]"
                    },
                    {
                        "internalType": "uint256",
                        "name": "timeline",
                        "type": "uint256"
                    },
                    {
                        "internalType": "address",
                        "name": "freelancer",
                        "type": "address"
                    },
                    {
                        "components": [
                            {
                                "internalType": "uint256",
                                "name": "jobId",
                                "type": "uint256"
                            },
                            {
                                "internalType": "string",
                                "name": "description",
                                "type": "string"
                            },
                            {
                                "internalType": "uint256",
                                "name": "timeline",
                                "type": "uint256"
                            },
                            {
                                "internalType": "address",
                                "name": "freelancer",
                                "type": "address"
                            },
                            {
                                "internalType": "enum BidState",
                                "name": "bidState",
                                "type": "uint8"
                            }
                        ],
                        "internalType": "struct Bid[]",
                        "name": "userBids",
                        "type": "tuple[]"
                    },
                    {
                        "internalType": "uint256",
                        "name": "timestamp",
                        "type": "uint256"
                    },
                    {
                        "internalType": "enum JobState",
                        "name": "state",
                        "type": "uint8"
                    },
                    {
                        "internalType": "string",
                        "name": "message",
                        "type": "string"
                    },
                    {
                        "internalType": "string",
                        "name": "url",
                        "type": "string"
                    }
                ],
                "internalType": "struct Job[]",
                "name": "",
                "type": "tuple[]"
            }
        ],
        "stateMutability": "view",
        "type": "function"
    },
    {
        "inputs": [
            {
                "internalType": "address",
                "name": "user",
                "type": "address"
            }
        ],
        "name": "getUser",
        "outputs": [
            {
                "components": [
                    {
                        "internalType": "string",
                        "name": "name",
                        "type": "string"
                    },
                    {
                        "internalType": "string",
                        "name": "bio",
                        "type": "string"
                    },
                    {
                        "internalType": "string",
                        "name": "mainSkill",
                        "type": "string"
                    },
                    {
                        "internalType": "string[]",
                        "name": "skills",
                        "type": "string[]"
                    },
                    {
                        "internalType": "string",
                        "name": "profileUrl",
                        "type": "string"
                    },
                    {
                        "internalType": "address",
                        "name": "user",
                        "type": "address"
                    }
                ],
                "internalType": "struct Profile",
                "name": "",
                "type": "tuple"
            }
        ],
        "stateMutability": "view",
        "type": "function"
    },
    {
        "inputs": [],
        "name": "getUserProfiles",
        "outputs": [
            {
                "components": [
                    {
                        "internalType": "string",
                        "name": "name",
                        "type": "string"
                    },
                    {
                        "internalType": "string",
                        "name": "bio",
                        "type": "string"
                    },
                    {
                        "internalType": "string",
                        "name": "mainSkill",
                        "type": "string"
                    },
                    {
                        "internalType": "string[]",
                        "name": "skills",
                        "type": "string[]"
                    },
                    {
                        "internalType": "string",
                        "name": "profileUrl",
                        "type": "string"
                    },
                    {
                        "internalType": "address",
                        "name": "user",
                        "type": "address"
                    }
                ],
                "internalType": "struct Profile[]",
                "name": "",
                "type": "tuple[]"
            }
        ],
        "stateMutability": "view",
        "type": "function"
    },
    {
        "inputs": [
            {
                "internalType": "uint256",
                "name": "",
                "type": "uint256"
            }
        ],
        "name": "jobs",
        "outputs": [
            {
                "internalType": "uint256",
                "name": "jobId",
                "type": "uint256"
            },
            {
                "internalType": "string",
                "name": "title",
                "type": "string"
            },
            {
                "internalType": "string",
                "name": "description",
                "type": "string"
            },
            {
                "internalType": "uint256",
                "name": "amount",
                "type": "uint256"
            },
            {
                "internalType": "address",
                "name": "client",
                "type": "address"
            },
            {
                "internalType": "uint256",
                "name": "timeline",
                "type": "uint256"
            },
            {
                "internalType": "address",
                "name": "freelancer",
                "type": "address"
            },
            {
                "internalType": "uint256",
                "name": "timestamp",
                "type": "uint256"
            },
            {
                "internalType": "enum JobState",
                "name": "state",
                "type": "uint8"
            },
            {
                "internalType": "string",
                "name": "message",
                "type": "string"
            },
            {
                "internalType": "string",
                "name": "url",
                "type": "string"
            }
        ],
        "stateMutability": "view",
        "type": "function"
    },
    {
        "inputs": [
            {
                "internalType": "uint256",
                "name": "jobId",
                "type": "uint256"
            }
        ],
        "name": "openDispute",
        "outputs": [
            {
                "components": [
                    {
                        "internalType": "uint256",
                        "name": "jobId",
                        "type": "uint256"
                    },
                    {
                        "internalType": "string",
                        "name": "title",
                        "type": "string"
                    },
                    {
                        "internalType": "string",
                        "name": "description",
                        "type": "string"
                    },
                    {
                        "internalType": "uint256",
                        "name": "amount",
                        "type": "uint256"
                    },
                    {
                        "internalType": "address",
                        "name": "client",
                        "type": "address"
                    },
                    {
                        "internalType": "string[]",
                        "name": "skills",
                        "type": "string[]"
                    },
                    {
                        "internalType": "uint256",
                        "name": "timeline",
                        "type": "uint256"
                    },
                    {
                        "internalType": "address",
                        "name": "freelancer",
                        "type": "address"
                    },
                    {
                        "components": [
                            {
                                "internalType": "uint256",
                                "name": "jobId",
                                "type": "uint256"
                            },
                            {
                                "internalType": "string",
                                "name": "description",
                                "type": "string"
                            },
                            {
                                "internalType": "uint256",
                                "name": "timeline",
                                "type": "uint256"
                            },
                            {
                                "internalType": "address",
                                "name": "freelancer",
                                "type": "address"
                            },
                            {
                                "internalType": "enum BidState",
                                "name": "bidState",
                                "type": "uint8"
                            }
                        ],
                        "internalType": "struct Bid[]",
                        "name": "userBids",
                        "type": "tuple[]"
                    },
                    {
                        "internalType": "uint256",
                        "name": "timestamp",
                        "type": "uint256"
                    },
                    {
                        "internalType": "enum JobState",
                        "name": "state",
                        "type": "uint8"
                    },
                    {
                        "internalType": "string",
                        "name": "message",
                        "type": "string"
                    },
                    {
                        "internalType": "string",
                        "name": "url",
                        "type": "string"
                    }
                ],
                "internalType": "struct Job",
                "name": "",
                "type": "tuple"
            }
        ],
        "stateMutability": "nonpayable",
        "type": "function"
    },
    {
        "inputs": [],
        "name": "owner",
        "outputs": [
            {
                "internalType": "address",
                "name": "",
                "type": "address"
            }
        ],
        "stateMutability": "view",
        "type": "function"
    },
    {
        "inputs": [
            {
                "internalType": "address",
                "name": "",
                "type": "address"
            }
        ],
        "name": "profile",
        "outputs": [
            {
                "internalType": "string",
                "name": "name",
                "type": "string"
            },
            {
                "internalType": "string",
                "name": "bio",
                "type": "string"
            },
            {
                "internalType": "string",
                "name": "mainSkill",
                "type": "string"
            },
            {
                "internalType": "string",
                "name": "profileUrl",
                "type": "string"
            },
            {
                "internalType": "address",
                "name": "user",
                "type": "address"
            }
        ],
        "stateMutability": "view",
        "type": "function"
    },
    {
        "inputs": [
            {
                "internalType": "uint256",
                "name": "",
                "type": "uint256"
            }
        ],
        "name": "profiles",
        "outputs": [
            {
                "internalType": "string",
                "name": "name",
                "type": "string"
            },
            {
                "internalType": "string",
                "name": "bio",
                "type": "string"
            },
            {
                "internalType": "string",
                "name": "mainSkill",
                "type": "string"
            },
            {
                "internalType": "string",
                "name": "profileUrl",
                "type": "string"
            },
            {
                "internalType": "address",
                "name": "user",
                "type": "address"
            }
        ],
        "stateMutability": "view",
        "type": "function"
    },
    {
        "inputs": [
            {
                "internalType": "uint256",
                "name": "jobId",
                "type": "uint256"
            }
        ],
        "name": "releasePayment",
        "outputs": [
            {
                "components": [
                    {
                        "internalType": "uint256",
                        "name": "jobId",
                        "type": "uint256"
                    },
                    {
                        "internalType": "string",
                        "name": "title",
                        "type": "string"
                    },
                    {
                        "internalType": "string",
                        "name": "description",
                        "type": "string"
                    },
                    {
                        "internalType": "uint256",
                        "name": "amount",
                        "type": "uint256"
                    },
                    {
                        "internalType": "address",
                        "name": "client",
                        "type": "address"
                    },
                    {
                        "internalType": "string[]",
                        "name": "skills",
                        "type": "string[]"
                    },
                    {
                        "internalType": "uint256",
                        "name": "timeline",
                        "type": "uint256"
                    },
                    {
                        "internalType": "address",
                        "name": "freelancer",
                        "type": "address"
                    },
                    {
                        "components": [
                            {
                                "internalType": "uint256",
                                "name": "jobId",
                                "type": "uint256"
                            },
                            {
                                "internalType": "string",
                                "name": "description",
                                "type": "string"
                            },
                            {
                                "internalType": "uint256",
                                "name": "timeline",
                                "type": "uint256"
                            },
                            {
                                "internalType": "address",
                                "name": "freelancer",
                                "type": "address"
                            },
                            {
                                "internalType": "enum BidState",
                                "name": "bidState",
                                "type": "uint8"
                            }
                        ],
                        "internalType": "struct Bid[]",
                        "name": "userBids",
                        "type": "tuple[]"
                    },
                    {
                        "internalType": "uint256",
                        "name": "timestamp",
                        "type": "uint256"
                    },
                    {
                        "internalType": "enum JobState",
                        "name": "state",
                        "type": "uint8"
                    },
                    {
                        "internalType": "string",
                        "name": "message",
                        "type": "string"
                    },
                    {
                        "internalType": "string",
                        "name": "url",
                        "type": "string"
                    }
                ],
                "internalType": "struct Job",
                "name": "",
                "type": "tuple"
            }
        ],
        "stateMutability": "nonpayable",
        "type": "function"
    },
    {
        "inputs": [],
        "name": "renounceOwnership",
        "outputs": [],
        "stateMutability": "nonpayable",
        "type": "function"
    },
    {
        "inputs": [
            {
                "internalType": "address",
                "name": "",
                "type": "address"
            },
            {
                "internalType": "uint256",
                "name": "",
                "type": "uint256"
            }
        ],
        "name": "reviews",
        "outputs": [
            {
                "internalType": "uint256",
                "name": "jobId",
                "type": "uint256"
            },
            {
                "internalType": "address",
                "name": "freelancer",
                "type": "address"
            },
            {
                "internalType": "string",
                "name": "review",
                "type": "string"
            },
            {
                "internalType": "uint256",
                "name": "rating",
                "type": "uint256"
            },
            {
                "internalType": "address",
                "name": "client",
                "type": "address"
            }
        ],
        "stateMutability": "view",
        "type": "function"
    },
    {
        "inputs": [
            {
                "internalType": "uint256",
                "name": "jobId",
                "type": "uint256"
            },
            {
                "internalType": "address",
                "name": "user",
                "type": "address"
            }
        ],
        "name": "sendContract",
        "outputs": [
            {
                "components": [
                    {
                        "internalType": "uint256",
                        "name": "jobId",
                        "type": "uint256"
                    },
                    {
                        "internalType": "string",
                        "name": "description",
                        "type": "string"
                    },
                    {
                        "internalType": "uint256",
                        "name": "timeline",
                        "type": "uint256"
                    },
                    {
                        "internalType": "address",
                        "name": "freelancer",
                        "type": "address"
                    },
                    {
                        "internalType": "enum BidState",
                        "name": "bidState",
                        "type": "uint8"
                    }
                ],
                "internalType": "struct Bid[]",
                "name": "",
                "type": "tuple[]"
            }
        ],
        "stateMutability": "nonpayable",
        "type": "function"
    },
    {
        "inputs": [
            {
                "internalType": "uint256",
                "name": "jobId",
                "type": "uint256"
            },
            {
                "internalType": "string",
                "name": "message",
                "type": "string"
            },
            {
                "internalType": "string",
                "name": "url",
                "type": "string"
            }
        ],
        "name": "submitJob",
        "outputs": [
            {
                "components": [
                    {
                        "internalType": "uint256",
                        "name": "jobId",
                        "type": "uint256"
                    },
                    {
                        "internalType": "string",
                        "name": "title",
                        "type": "string"
                    },
                    {
                        "internalType": "string",
                        "name": "description",
                        "type": "string"
                    },
                    {
                        "internalType": "uint256",
                        "name": "amount",
                        "type": "uint256"
                    },
                    {
                        "internalType": "address",
                        "name": "client",
                        "type": "address"
                    },
                    {
                        "internalType": "string[]",
                        "name": "skills",
                        "type": "string[]"
                    },
                    {
                        "internalType": "uint256",
                        "name": "timeline",
                        "type": "uint256"
                    },
                    {
                        "internalType": "address",
                        "name": "freelancer",
                        "type": "address"
                    },
                    {
                        "components": [
                            {
                                "internalType": "uint256",
                                "name": "jobId",
                                "type": "uint256"
                            },
                            {
                                "internalType": "string",
                                "name": "description",
                                "type": "string"
                            },
                            {
                                "internalType": "uint256",
                                "name": "timeline",
                                "type": "uint256"
                            },
                            {
                                "internalType": "address",
                                "name": "freelancer",
                                "type": "address"
                            },
                            {
                                "internalType": "enum BidState",
                                "name": "bidState",
                                "type": "uint8"
                            }
                        ],
                        "internalType": "struct Bid[]",
                        "name": "userBids",
                        "type": "tuple[]"
                    },
                    {
                        "internalType": "uint256",
                        "name": "timestamp",
                        "type": "uint256"
                    },
                    {
                        "internalType": "enum JobState",
                        "name": "state",
                        "type": "uint8"
                    },
                    {
                        "internalType": "string",
                        "name": "message",
                        "type": "string"
                    },
                    {
                        "internalType": "string",
                        "name": "url",
                        "type": "string"
                    }
                ],
                "internalType": "struct Job",
                "name": "",
                "type": "tuple"
            }
        ],
        "stateMutability": "nonpayable",
        "type": "function"
    },
    {
        "inputs": [
            {
                "internalType": "uint256",
                "name": "jobId",
                "type": "uint256"
            },
            {
                "internalType": "string",
                "name": "description",
                "type": "string"
            },
            {
                "internalType": "uint256",
                "name": "timeline",
                "type": "uint256"
            }
        ],
        "name": "submitProposal",
        "outputs": [],
        "stateMutability": "nonpayable",
        "type": "function"
    },
    {
        "inputs": [
            {
                "internalType": "address",
                "name": "newOwner",
                "type": "address"
            }
        ],
        "name": "transferOwnership",
        "outputs": [],
        "stateMutability": "nonpayable",
        "type": "function"
    },
    {
        "inputs": [
            {
                "internalType": "uint256",
                "name": "_listPrice",
                "type": "uint256"
            }
        ],
        "name": "updateListPrice",
        "outputs": [],
        "stateMutability": "nonpayable",
        "type": "function"
    },
    {
        "inputs": [],
        "name": "withdraw",
        "outputs": [],
        "stateMutability": "nonpayable",
        "type": "function"
    },
    {
        "inputs": [
            {
                "internalType": "uint256",
                "name": "jobId",
                "type": "uint256"
            }
        ],
        "name": "withdrawOffer",
        "outputs": [
            {
                "components": [
                    {
                        "internalType": "uint256",
                        "name": "jobId",
                        "type": "uint256"
                    },
                    {
                        "internalType": "string",
                        "name": "description",
                        "type": "string"
                    },
                    {
                        "internalType": "uint256",
                        "name": "timeline",
                        "type": "uint256"
                    },
                    {
                        "internalType": "address",
                        "name": "freelancer",
                        "type": "address"
                    },
                    {
                        "internalType": "enum BidState",
                        "name": "bidState",
                        "type": "uint8"
                    }
                ],
                "internalType": "struct Bid[]",
                "name": "",
                "type": "tuple[]"
            }
        ],
        "stateMutability": "nonpayable",
        "type": "function"
    },
    {
        "inputs": [
            {
                "internalType": "contract IERC20",
                "name": "token",
                "type": "address"
            }
        ],
        "name": "withdrawTokens",
        "outputs": [],
        "stateMutability": "nonpayable",
        "type": "function"
    }
]